explainaboard_client/__init__.py
explainaboard_client/__main__.py
explainaboard_client/client.py
explainaboard_client/client_utils.py
explainaboard_client/config.py
explainaboard_client/data_utils.py
explainaboard_client/exceptions.py
explainaboard_client/tasks.py
explainaboard_client/cli/__init__.py
explainaboard_client/cli/delete_systems.py
explainaboard_client/cli/evaluate_benchmark.py
explainaboard_client/cli/evaluate_system.py
explainaboard_client/cli/find_systems.py
explainaboard_client/cli/upload_benchmark.py
explainaboard_client/cli/upload_system.py
explainaboard_client/tests/__init__.py
explainaboard_client/tests/test_benchmark.py
explainaboard_client/tests/test_check_api_version.py
explainaboard_client/tests/test_cli.py
explainaboard_client/tests/test_info.py
explainaboard_client/tests/test_system.py
explainaboard_client/tests/test_tabular.py
explainaboard_client/tests/test_user.py
explainaboard_client/tests/test_utils.py
explainaboard_client-0.1.4.dist-info/METADATA
explainaboard_client-0.1.4.dist-info/WHEEL
explainaboard_client-0.1.4.dist-info/entry_points.txt
explainaboard_client-0.1.4.dist-info/top_level.txt
explainaboard_client-0.1.4.dist-info/RECORD
