Metadata-Version: 2.1
Name: explainaboard-client
Version: 0.1.4
Summary: ExplainaBoard Client
Home-page: https://github.com/neulab/explainaboard_client
License: MIT License
Platform: UNKNOWN
Classifier: Intended Audience :: Developers
Classifier: Topic :: Text Processing
Classifier: Topic :: Scientific/Engineering :: Artificial Intelligence
Classifier: License :: OSI Approved :: MIT License
Classifier: Programming Language :: Python :: 3.9
Classifier: Programming Language :: Python :: 3.10
Classifier: Programming Language :: Python :: 3 :: Only
Requires-Dist: explainaboard-api-client (>=0.4.3)
Provides-Extra: dev
Requires-Dist: pre-commit ; extra == 'dev'
